nbmodular/__init__.py
nbmodular/_modidx.py
nbmodular/index.py
nbmodular/core/__init__.py
nbmodular/core/cell2func.py
nbmodular/core/function_io.py
nbmodular/core/nbdev_sync.py
nbmodular-0.0.22.dist-info/LICENSE
nbmodular-0.0.22.dist-info/METADATA
nbmodular-0.0.22.dist-info/WHEEL
nbmodular-0.0.22.dist-info/entry_points.txt
nbmodular-0.0.22.dist-info/top_level.txt
nbmodular-0.0.22.dist-info/RECORD
