Metadata-Version: 2.1
Name: nbmodular
Version: 0.0.22
Summary: Convert notebooks to modular code
Home-page: https://github.com/JaumeAmoresDS/nbmodular
Author: Jaume Amores
Author-email: jaume.dsdev@gmail.com
License: Apache Software License 2.0
Keywords: nbdev jupyter notebook python
Classifier: Development Status :: 4 - Beta
Classifier: Intended Audience :: Developers
Classifier: Natural Language :: English
Classifier: Programming Language :: Python :: 3.7
Classifier: Programming Language :: Python :: 3.8
Classifier: Programming Language :: Python :: 3.9
Classifier: Programming Language :: Python :: 3.10
Classifier: License :: OSI Approved :: Apache Software License
Requires-Python: >=3.7
License-File: LICENSE
Requires-Dist: fastcore
Requires-Dist: nbdev
Requires-Dist: pandas
Requires-Dist: ipynbname
Requires-Dist: scikit-learn
Requires-Dist: fastdot
Provides-Extra: dev
Requires-Dist: pytest ; extra == 'dev'
